jupyterlab_rtc/__init__.py
jupyterlab_rtc/_version.py
jupyterlab_rtc/handlers.py
jupyterlab_rtc/tests/__init__.py
jupyterlab_rtc/tests/test_handlers.py
jupyterlab_rtc-0.0.5.data/data/etc/jupyter/jupyter_notebook_config.d/jupyterlab_rtc.json
jupyterlab_rtc-0.0.5.data/data/etc/jupyter/jupyter_server_config.d/jupyterlab_rtc.json
jupyterlab_rtc-0.0.5.data/data/share/jupyter/labextensions/@datalayer/jupyterlab-rtc/build_log.json
jupyterlab_rtc-0.0.5.data/data/share/jupyter/labextensions/@datalayer/jupyterlab-rtc/package.json
jupyterlab_rtc-0.0.5.data/data/share/jupyter/labextensions/@datalayer/jupyterlab-rtc/schemas/@datalayer/jupyterlab-rtc/package.json.orig
jupyterlab_rtc-0.0.5.data/data/share/jupyter/labextensions/@datalayer/jupyterlab-rtc/schemas/@datalayer/jupyterlab-rtc/plugin.json
jupyterlab_rtc-0.0.5.data/data/share/jupyter/labextensions/@datalayer/jupyterlab-rtc/static/lib_index_js.59f9f408d74f9b19b5f9.js
jupyterlab_rtc-0.0.5.data/data/share/jupyter/labextensions/@datalayer/jupyterlab-rtc/static/lib_index_js.59f9f408d74f9b19b5f9.js.map
jupyterlab_rtc-0.0.5.data/data/share/jupyter/labextensions/@datalayer/jupyterlab-rtc/static/remoteEntry.0367883fcdd2d99c10c0.js
jupyterlab_rtc-0.0.5.data/data/share/jupyter/labextensions/@datalayer/jupyterlab-rtc/static/remoteEntry.0367883fcdd2d99c10c0.js.map
jupyterlab_rtc-0.0.5.data/data/share/jupyter/labextensions/@datalayer/jupyterlab-rtc/static/style.js
jupyterlab_rtc-0.0.5.data/data/share/jupyter/labextensions/@datalayer/jupyterlab-rtc/static/style_index_js.1c875799670b0d607402.js
jupyterlab_rtc-0.0.5.data/data/share/jupyter/labextensions/@datalayer/jupyterlab-rtc/static/style_index_js.1c875799670b0d607402.js.map
jupyterlab_rtc-0.0.5.data/data/share/jupyter/labextensions/@datalayer/jupyterlab-rtc/static/vendors-node_modules_css-loader_dist_runtime_api_js-node_modules_css-loader_dist_runtime_cssW-72eba1.f8f76f10199f76bb7ca6.js
jupyterlab_rtc-0.0.5.dist-info/METADATA
jupyterlab_rtc-0.0.5.dist-info/WHEEL
jupyterlab_rtc-0.0.5.dist-info/licenses/LICENSE
jupyterlab_rtc-0.0.5.dist-info/RECORD
